gctts.py
gctts-1.2.dist-info/LICENSE
gctts-1.2.dist-info/METADATA
gctts-1.2.dist-info/WHEEL
gctts-1.2.dist-info/entry_points.txt
gctts-1.2.dist-info/top_level.txt
gctts-1.2.dist-info/RECORD
