Metadata-Version: 2.1
Name: gctts
Version: 1.2
Summary: A simple way to generate high quality TTS MP3 files.
Home-page: https://github.com/JamesClick/gctts
Author: J. Click
License: MIT
Platform: UNKNOWN
Classifier: Development Status :: 4 - Beta
Classifier: Intended Audience :: Developers
Classifier: License :: OSI Approved :: MIT License
Classifier: Programming Language :: Python :: 3.7
Requires-Dist: Click
Requires-Dist: requests
